and_gate.v
module and_gate(input wire A,input wire B,output wire O);
    assign O=A&B;
endmodule

half_adder.v
module half_adder(input A,input B,output S,output C);
    and_gate andGate(.A(A),.B(B),.O(C));
    assign S=A^B;
endmodule

2x2_binary_multiplier.v
module binary_multiplier(input A0,A1,B0,B1 ,output M0,M1,M2,M3);

    and_gate ag1(A0,B0,M0);
    wire x,y;
    and_gate ag2(A1,B0,x);
    and_gate ag3(A0,B1,y);
    wire c;
    half_adder ha1(x,y,M1,c);
    wire z;
    and_gate ag4(B1,A1,z);
    half_adder ha2(z,c,M2,M3);

endmodule

2x2_binary_multiplier_tb.v
module binary_multiplier_tb;
    reg A0,A1,B0,B1;
    wire M0,M1,M2,M3;
    integer i;

    binary_multiplier bm(A0,A1,B0,B1,M0,M1,M2,M3);

    initial begin

        $dumpfile("2x2_binary_multiplier_output.vcd");
        $dumpvars(0,binary_multiplier_tb);

        $monitor("Time=%2d | A1A0=%b%b B1B0=%b%b | S3S2S1S0=%b%b%b%b",$time,A1,A0,B1,B0,M3,M2,M1,M0);

        for(i=0;i<16;i=i+1)begin
            {A0,A1,B0,B1}=i;
            #10;
        end

        $finish;
    end
endmodule

2x2_binary_multiplier_output.vcd
$date
	Sun Nov  9 20:05:19 2025
$end
$version
	Icarus Verilog
$end
$timescale
	1s
$end
$scope module binary_multiplier_tb $end
$var wire 1 ! M3 $end
$var wire 1 " M2 $end
$var wire 1 # M1 $end
$var wire 1 $ M0 $end
$var reg 1 % A0 $end
$var reg 1 & A1 $end
$var reg 1 ' B0 $end
$var reg 1 ( B1 $end
$var integer 32 ) i [31:0] $end
$scope module bm $end
$var wire 1 % A0 $end
$var wire 1 & A1 $end
$var wire 1 ' B0 $end
$var wire 1 ( B1 $end
$var wire 1 * z $end
$var wire 1 + y $end
$var wire 1 , x $end
$var wire 1 - c $end
$var wire 1 ! M3 $end
$var wire 1 " M2 $end
$var wire 1 # M1 $end
$var wire 1 $ M0 $end
$scope module ag1 $end
$var wire 1 % A $end
$var wire 1 ' B $end
$var wire 1 $ O $end
$upscope $end
$scope module ag2 $end
$var wire 1 & A $end
$var wire 1 ' B $end
$var wire 1 , O $end
$upscope $end
$scope module ag3 $end
$var wire 1 % A $end
$var wire 1 ( B $end
$var wire 1 + O $end
$upscope $end
$scope module ag4 $end
$var wire 1 ( A $end
$var wire 1 & B $end
$var wire 1 * O $end
$upscope $end
$scope module ha1 $end
$var wire 1 , A $end
$var wire 1 + B $end
$var wire 1 # S $end
$var wire 1 - C $end
$scope module andGate $end
$var wire 1 , A $end
$var wire 1 + B $end
$var wire 1 - O $end
$upscope $end
$upscope $end
$scope module ha2 $end
$var wire 1 * A $end
$var wire 1 - B $end
$var wire 1 " S $end
$var wire 1 ! C $end
$scope module andGate $end
$var wire 1 * A $end
$var wire 1 - B $end
$var wire 1 ! O $end
$upscope $end
$upscope $end
$upscope $end
$upscope $end
$enddefinitions $end
$comment Show the parameter values. $end
$dumpall
$end
#0
$dumpvars
0-
0,
0+
0*
b0 )
0(
0'
0&
0%
0$
0#
0"
0!
$end
#10
1(
b1 )
#20
1'
0(
b10 )
#30
1(
b11 )
#40
1&
0'
0(
b100 )
#50
1"
1*
1(
b101 )
#60
1#
0"
1,
0*
1'
0(
b110 )
#70
1"
1*
1(
b111 )
#80
0#
0"
0,
0*
1%
0&
0'
0(
b1000 )
#90
1#
1+
1(
b1001 )
#100
0#
1$
0+
1'
0(
b1010 )
#110
1#
1+
1(
b1011 )
#120
0#
0$
0+
1&
0'
0(
b1100 )
#130
1#
1"
1+
1*
1(
b1101 )
#140
0"
1$
1,
0+
0*
1'
0(
b1110 )
#150
1!
0#
1-
0"
1+
1*
1(
b1111 )
#160
b10000 )
