nand_gate.v
module nand_gate(input a,b,c ,output o);
    assign o=~(a&b&c);
endmodule

decoder.v
module decoder(input en,a,b, output d0,d1,d2,d3);
    wire a_inv,b_inv,en_inv;
    nand_gate ng1(a,a,a,a_inv);
    nand_gate ng2(b,b,b,b_inv);
    nand_gate ng3(en,en,en,en_inv);

    nand_gate ng4(a,b,en_inv,d3);
    nand_gate ng5(a,b_inv,en_inv,d2);
    nand_gate ng6(a_inv,b,en_inv,d1);
    nand_gate ng7(a_inv,b_inv,en_inv,d0);

endmodule

decoder_tb.v
module decoder_tb;
    reg en,a,b;
    wire d0,d1,d2,d3;
    integer i;

    decoder d(en,a,b,d0,d1,d2,d3);

    initial begin
        $dumpfile("decoder_output.vcd");
        $dumpvars(0,decoder_tb);

        $monitor("Time=%2d | En=%b A=%b B=%b | D3=%b D2=%b D1=%b D0=%b",$time,en,a,b,d3,d2,d1,d0);

        for(i=0;i<8;i=i+1)begin
            {en,a,b}=i;
            #10;
        end

        $finish;
    end
endmodule

decoder_output.vcd
$date
	Sun Nov  9 22:46:39 2025
$end
$version
	Icarus Verilog
$end
$timescale
	1s
$end
$scope module decoder_tb $end
$var wire 1 ! d3 $end
$var wire 1 " d2 $end
$var wire 1 # d1 $end
$var wire 1 $ d0 $end
$var reg 1 % a $end
$var reg 1 & b $end
$var reg 1 ' en $end
$var integer 32 ( i [31:0] $end
$scope module d $end
$var wire 1 % a $end
$var wire 1 & b $end
$var wire 1 ' en $end
$var wire 1 ) en_inv $end
$var wire 1 ! d3 $end
$var wire 1 " d2 $end
$var wire 1 # d1 $end
$var wire 1 $ d0 $end
$var wire 1 * b_inv $end
$var wire 1 + a_inv $end
$scope module ng1 $end
$var wire 1 % a $end
$var wire 1 % b $end
$var wire 1 % c $end
$var wire 1 + o $end
$upscope $end
$scope module ng2 $end
$var wire 1 & a $end
$var wire 1 & b $end
$var wire 1 & c $end
$var wire 1 * o $end
$upscope $end
$scope module ng3 $end
$var wire 1 ' a $end
$var wire 1 ' b $end
$var wire 1 ' c $end
$var wire 1 ) o $end
$upscope $end
$scope module ng4 $end
$var wire 1 % a $end
$var wire 1 & b $end
$var wire 1 ) c $end
$var wire 1 ! o $end
$upscope $end
$scope module ng5 $end
$var wire 1 % a $end
$var wire 1 * b $end
$var wire 1 ) c $end
$var wire 1 " o $end
$upscope $end
$scope module ng6 $end
$var wire 1 + a $end
$var wire 1 & b $end
$var wire 1 ) c $end
$var wire 1 # o $end
$upscope $end
$scope module ng7 $end
$var wire 1 + a $end
$var wire 1 * b $end
$var wire 1 ) c $end
$var wire 1 $ o $end
$upscope $end
$upscope $end
$upscope $end
$enddefinitions $end
$comment Show the parameter values. $end
$dumpall
$end
#0
$dumpvars
1+
1*
1)
b0 (
0'
0&
0%
0$
1#
1"
1!
$end
#10
1$
0*
0#
1&
b1 (
#20
0"
1$
0+
1#
1*
1%
0&
b10 (
#30
1"
0*
0!
1&
b11 (
#40
0)
1!
1+
1*
1'
0%
0&
b100 (
#50
0*
1&
b101 (
#60
0+
1*
1%
0&
b110 (
#70
0*
1&
b111 (
#80
b1000 (
