nand_gate.v
module nand_gate(input a,b,c ,output o);
    assign o=~(a&b&c);
endmodule

decoder.v
module decoder(input en,a,b, output d0,d1,d2,d3);
    wire a_inv,b_inv,en_inv;
    nand_gate ng1(a,a,a,a_inv);
    nand_gate ng2(b,b,b,b_inv);
    nand_gate ng3(en,en,en,en_inv);

    nand_gate ng4(a,b,en_inv,d3);
    nand_gate ng5(a,b_inv,en_inv,d2);
    nand_gate ng6(a_inv,b,en_inv,d1);
    nand_gate ng7(a_inv,b_inv,en_inv,d0);

endmodule

decoder3x8.v
module decoder3x8(input en,a, b, c, output d0, d1, d2, d3, d4, d5, d6, d7);

    wire a_inv;
    nand_gate inv_a(a, a, a, a_inv);
    decoder d_low(en|a, b, c, d0, d1, d2, d3);
    decoder d_high(en|a_inv, b, c, d4, d5, d6, d7);

endmodule

decoder3x8_tb.v
module decoder3x8_tb;
    reg en,a,b,c;
    wire d0,d1,d2,d3,d4,d5,d6,d7;
    integer i;

    decoder3x8 d(en,a,b,c,d0,d1,d2,d3,d4,d5,d6,d7);

    initial begin
        $dumpfile("decoder3x8_output.vcd");
        $dumpvars(0,decoder3x8_tb);

        $monitor("Time=%2d | En=%d A=%d B=%d C=%d | D7=%d D6=%d D5=%d D4=%d D3=%d D2=%d D1=%d D0=%d",$time,en,a,b,c,d7,d6,d5,d4,d3,d2,d1,d0);

        for(i=0;i<16;i=i+1)begin
            {en,a,b,c}=i;
            #10;
        end
    $finish;

    end
endmodule

decoder3x8_output.vcd
$date
	Sun Nov  9 23:49:25 2025
$end
$version
	Icarus Verilog
$end
$timescale
	1s
$end
$scope module decoder3x8_tb $end
$var wire 1 ! d7 $end
$var wire 1 " d6 $end
$var wire 1 # d5 $end
$var wire 1 $ d4 $end
$var wire 1 % d3 $end
$var wire 1 & d2 $end
$var wire 1 ' d1 $end
$var wire 1 ( d0 $end
$var reg 1 ) a $end
$var reg 1 * b $end
$var reg 1 + c $end
$var reg 1 , en $end
$var integer 32 - i [31:0] $end
$scope module d $end
$var wire 1 ) a $end
$var wire 1 * b $end
$var wire 1 + c $end
$var wire 1 , en $end
$var wire 1 ! d7 $end
$var wire 1 " d6 $end
$var wire 1 # d5 $end
$var wire 1 $ d4 $end
$var wire 1 % d3 $end
$var wire 1 & d2 $end
$var wire 1 ' d1 $end
$var wire 1 ( d0 $end
$var wire 1 . a_inv $end
$scope module d_high $end
$var wire 1 * a $end
$var wire 1 + b $end
$var wire 1 / en $end
$var wire 1 0 en_inv $end
$var wire 1 ! d3 $end
$var wire 1 " d2 $end
$var wire 1 # d1 $end
$var wire 1 $ d0 $end
$var wire 1 1 b_inv $end
$var wire 1 2 a_inv $end
$scope module ng1 $end
$var wire 1 * a $end
$var wire 1 * b $end
$var wire 1 * c $end
$var wire 1 2 o $end
$upscope $end
$scope module ng2 $end
$var wire 1 + a $end
$var wire 1 + b $end
$var wire 1 + c $end
$var wire 1 1 o $end
$upscope $end
$scope module ng3 $end
$var wire 1 / a $end
$var wire 1 / b $end
$var wire 1 / c $end
$var wire 1 0 o $end
$upscope $end
$scope module ng4 $end
$var wire 1 * a $end
$var wire 1 + b $end
$var wire 1 0 c $end
$var wire 1 ! o $end
$upscope $end
$scope module ng5 $end
$var wire 1 * a $end
$var wire 1 1 b $end
$var wire 1 0 c $end
$var wire 1 " o $end
$upscope $end
$scope module ng6 $end
$var wire 1 2 a $end
$var wire 1 + b $end
$var wire 1 0 c $end
$var wire 1 # o $end
$upscope $end
$scope module ng7 $end
$var wire 1 2 a $end
$var wire 1 1 b $end
$var wire 1 0 c $end
$var wire 1 $ o $end
$upscope $end
$upscope $end
$scope module d_low $end
$var wire 1 * a $end
$var wire 1 + b $end
$var wire 1 3 en $end
$var wire 1 4 en_inv $end
$var wire 1 % d3 $end
$var wire 1 & d2 $end
$var wire 1 ' d1 $end
$var wire 1 ( d0 $end
$var wire 1 5 b_inv $end
$var wire 1 6 a_inv $end
$scope module ng1 $end
$var wire 1 * a $end
$var wire 1 * b $end
$var wire 1 * c $end
$var wire 1 6 o $end
$upscope $end
$scope module ng2 $end
$var wire 1 + a $end
$var wire 1 + b $end
$var wire 1 + c $end
$var wire 1 5 o $end
$upscope $end
$scope module ng3 $end
$var wire 1 3 a $end
$var wire 1 3 b $end
$var wire 1 3 c $end
$var wire 1 4 o $end
$upscope $end
$scope module ng4 $end
$var wire 1 * a $end
$var wire 1 + b $end
$var wire 1 4 c $end
$var wire 1 % o $end
$upscope $end
$scope module ng5 $end
$var wire 1 * a $end
$var wire 1 5 b $end
$var wire 1 4 c $end
$var wire 1 & o $end
$upscope $end
$scope module ng6 $end
$var wire 1 6 a $end
$var wire 1 + b $end
$var wire 1 4 c $end
$var wire 1 ' o $end
$upscope $end
$scope module ng7 $end
$var wire 1 6 a $end
$var wire 1 5 b $end
$var wire 1 4 c $end
$var wire 1 ( o $end
$upscope $end
$upscope $end
$scope module inv_a $end
$var wire 1 ) a $end
$var wire 1 ) b $end
$var wire 1 ) c $end
$var wire 1 . o $end
$upscope $end
$upscope $end
$upscope $end
$enddefinitions $end
$comment Show the parameter values. $end
$dumpall
$end
#0
$dumpvars
16
15
14
03
12
11
00
1/
1.
b0 -
0,
0+
0*
0)
0(
1'
1&
1%
1$
1#
1"
1!
$end
#10
1(
01
05
0'
1+
b1 -
#20
0&
1(
02
06
1'
11
15
1*
0+
b10 -
#30
1&
01
05
0%
1+
b11 -
#40
0$
10
1(
04
0/
0.
1%
12
16
11
15
13
1)
0*
0+
b100 -
#50
1$
01
0#
05
1+
b101 -
#60
0"
1$
02
06
1#
11
15
1*
0+
b110 -
#70
1"
01
0!
05
1+
b111 -
#80
1$
00
1!
1.
12
16
11
15
1/
1,
0)
0*
0+
b1000 -
#90
01
05
1+
b1001 -
#100
02
06
11
15
1*
0+
b1010 -
#110
01
05
1+
b1011 -
#120
0.
12
16
11
15
1)
0*
0+
b1100 -
#130
01
05
1+
b1101 -
#140
02
06
11
15
1*
0+
b1110 -
#150
01
05
1+
b1111 -
#160
b10000 -
