nand_gate.v
module nand_gate(input a,b,c ,output o);
    assign o=~(a&b&c);
endmodule

nand_gate_tb.v
module nand_gate_tb;
    reg a,b,c;
    wire o;
    integer i;

    nand_gate ng(a,b,c,o);

    initial begin
        $dumpfile("nand_gate_output.vcd");
        $dumpvars(0,nand_gate_tb);

        $monitor("Time=%2d | A=%b B=%b C=%b | O=%b",$time,a,b,c,o);

        for(i=0;i<8;i=i+1)begin
            {a,b,c}=i;
            #10;
        end

        $finish;
    end
endmodule

nand_gate_output.vcd
$date
	Sun Nov  9 22:28:43 2025
$end
$version
	Icarus Verilog
$end
$timescale
	1s
$end
$scope module nand_gate_tb $end
$var wire 1 ! o $end
$var reg 1 " a $end
$var reg 1 # b $end
$var reg 1 $ c $end
$var integer 32 % i [31:0] $end
$scope module ng $end
$var wire 1 " a $end
$var wire 1 # b $end
$var wire 1 $ c $end
$var wire 1 ! o $end
$upscope $end
$upscope $end
$enddefinitions $end
$comment Show the parameter values. $end
$dumpall
$end
#0
$dumpvars
b0 %
0$
0#
0"
1!
$end
#10
1$
b1 %
#20
1#
0$
b10 %
#30
1$
b11 %
#40
1"
0#
0$
b100 %
#50
1$
b101 %
#60
1#
0$
b110 %
#70
0!
1$
b111 %
#80
b1000 %
